MANIFEST.in
README.rst
setup.py
collective/__init__.py
collective/__init__.pyc
collective.ptg.bootstrapcarousel.egg-info/PKG-INFO
collective.ptg.bootstrapcarousel.egg-info/SOURCES.txt
collective.ptg.bootstrapcarousel.egg-info/dependency_links.txt
collective.ptg.bootstrapcarousel.egg-info/entry_points.txt
collective.ptg.bootstrapcarousel.egg-info/namespace_packages.txt
collective.ptg.bootstrapcarousel.egg-info/not-zip-safe
collective.ptg.bootstrapcarousel.egg-info/requires.txt
collective.ptg.bootstrapcarousel.egg-info/top_level.txt
collective/ptg/__init__.py
collective/ptg/__init__.pyc
collective/ptg/bootstrapcarousel/__init__.py
collective/ptg/bootstrapcarousel/__init__.pyc
collective/ptg/bootstrapcarousel/bootstrapcarousel.pt
collective/ptg/bootstrapcarousel/configure.zcml
collective/ptg/bootstrapcarousel/resources/bootstrap.min.css
collective/ptg/bootstrapcarousel/resources/bootstrap.min.js
docs/HISTORY.txt
docs/INSTALL.txt
docs/LICENSE.GPL
docs/LICENSE.txt