Metadata-Version: 1.1
Name: collective.ptg.bootstrapcarousel
Version: 1.0.1
Summary: Add Bootstraps Carousel to collective.plonetruegallery
Home-page: https://github.com/jsonmurphy/collective.ptg.boostrapcarousel
Author: Jason Murphy
Author-email: json.murphy@gmail.com
License: GPL
Keywords: plone plonetruegallery addon
Platform: UNKNOWN
Classifier: Framework :: Plone
Classifier: Programming Language :: Python
